winuvloop/__init__.py
winuvloop-0.2.0.dist-info/LICENSE
winuvloop-0.2.0.dist-info/METADATA
winuvloop-0.2.0.dist-info/WHEEL
winuvloop-0.2.0.dist-info/RECORD
