Metadata-Version: 2.1
Name: winuvloop
Version: 0.2.0
Summary: winuvloop is a Python package that automatically installs and configures the optimal event loop for your platform, setting up uvloop on Linux/POSIX systems and winloop on Windows, ensuring seamless cross-platform development.
License: MIT
Author: Aviad Rozenhek
Author-email: aviadr1@gmail.com
Requires-Python: >=3.11,<4.0
Classifier: License :: OSI Approved :: MIT License
Classifier: Programming Language :: Python :: 3
Classifier: Programming Language :: Python :: 3.11
Classifier: Programming Language :: Python :: 3.12
Requires-Dist: uvloop ; sys_platform != "win32"
Requires-Dist: winloop ; sys_platform == "win32"
